Metadata-Version: 1.0
Name: pysharefile
Version: 0.7
Summary: Utility modules for working with Sharefile in python 3
Home-page: http://github.com/storborg/funniest
Author: Austin Nafziger
Author-email: anafziger@42northrx.com
License: MIT
Platform: UNKNOWN
